[
    {
        "id": "0000",
        "line": {
            "en": "'Hurry up!'"
        },
        "name": "Kotori"
    },
    {
        "id": "0400",
        "line": {
            "en": "'There's no need to rush.'"
        },
        "name": "Aoi"
    },
    {
        "id": "0800",
        "line": {
            "en": "I had just finished checking out, and left the\\nconvenience store to catch up to Kotori, who had\\nleft first with a bag on her lap."
        },
        "name": ""
    },
    {
        "id": "0c00",
        "line": {
            "en": "I grabbed the wheelchair's handlebars."
        },
        "name": ""
    },
    {
        "id": "1000",
        "line": {
            "en": "'Let's go, Kotori! Hold on tight!'"
        },
        "name": "Aoi"
    },
    {
        "id": "1400",
        "line": {
            "en": "'Aaaalright, goooo!'"
        },
        "name": "Kotori"
    },
    {
        "id": "1800",
        "line": {
            "en": "At Kotori's signal, I pushed the wheelchair as\\nfast as I could."
        },
        "name": ""
    },
    {
        "id": "1c00",
        "line": {
            "en": "'Huff... puff... huff... puff...'"
        },
        "name": "Aoi"
    },
    {
        "id": "2000",
        "line": {
            "en": "'Hey, are you okay?'"
        },
        "name": "Kotori"
    },
    {
        "id": "2400",
        "line": {
            "en": "'I'm... okay! I'm fine!'"
        },
        "name": "Aoi"
    },
    {
        "id": "2800",
        "line": {
            "en": "I try to act tough, but I can't hide the fact\\nthat I'm out of breath."
        },
        "name": ""
    },
    {
        "id": "2c00",
        "line": {
            "en": "'Haa... haa... My stamina's gotten worse...'"
        },
        "name": "Aoi"
    },
    {
        "id": "3000",
        "line": {
            "en": "I've been running with the wheelchair this far\\nbut my stamina isn't what it used to be."
        },
        "name": ""
    },
    {
        "id": "3400",
        "line": {
            "en": "She couldn't help but notice, so Kotori took a\\nsports drink out of the bag."
        },
        "name": ""
    },
    {
        "id": "3800",
        "line": {
            "en": "'Here, Aoi.'"
        },
        "name": "Kotori"
    },
    {
        "id": "3c00",
        "line": {
            "en": "'Thanks...'"
        },
        "name": "Aoi"
    },
    {
        "id": "4000",
        "line": {
            "en": "'You're getting a bit carried away... is your\\nknee okay?'"
        },
        "name": "Kotori"
    },
    {
        "id": "4400",
        "line": {
            "en": "'My knee? Yeah, no problem. ...I think.'"
        },
        "name": "Aoi"
    },
    {
        "id": "4800",
        "line": {
            "en": "According to the doctor, I shouldn't have any\\ndifficulty with everyday life."
        },
        "name": ""
    },
    {
        "id": "4c00",
        "line": {
            "en": "The problem is whether or not this is above the\\nlevel of everyday activity."
        },
        "name": ""
    },
    {
        "id": "5000",
        "line": {
            "en": "'I told you halfway that you could stop, but you\\nran all the way to school...'"
        },
        "name": "Kotori"
    },
    {
        "id": "5400",
        "line": {
            "en": "I'm in a good mood, and have been since this\\nmorning."
        },
        "name": ""
    },
    {
        "id": "5800",
        "line": {
            "en": "Our club activities are finally about to start."
        },
        "name": ""
    },
    {
        "id": "5c00",
        "line": {
            "en": "It's Saturday, a day off, but we got up early and\\ncame to school."
        },
        "name": ""
    },
    {
        "id": "6000",
        "line": {
            "en": "'...You went through all the effort to get\\nbetter, so take care of yourself, okay?'"
        },
        "name": "Kotori"
    },
    {
        "id": "6400",
        "line": {
            "en": "'You're right.'"
        },
        "name": "Aoi"
    },
    {
        "id": "6800",
        "line": {
            "en": "I finish talking, and take a drink."
        },
        "name": ""
    },
    {
        "id": "6c00",
        "line": {
            "en": "I've been sweating a lot, so my body quickly\\nabsorbs the sports drink."
        },
        "name": ""
    },
    {
        "id": "7000",
        "line": {
            "en": "'What about your knee?'"
        },
        "name": "Ageha"
    },
    {
        "id": "7400",
        "line": {
            "en": "'Pfooo! ...Cough, cough!'"
        },
        "name": "Aoi"
    },
    {
        "id": "7800",
        "line": {
            "en": "Ageha came out of nowhere, and stood right next\\nto me."
        },
        "name": ""
    },
    {
        "id": "7c00",
        "line": {
            "en": "'It-It's nothing, no big deal.'"
        },
        "name": "Aoi"
    },
    {
        "id": "8000",
        "line": {
            "en": "'Hmm.'"
        },
        "name": "Ageha"
    },
    {
        "id": "8400",
        "line": {
            "en": "'Morning, Kotori.'"
        },
        "name": "Ageha"
    },
    {
        "id": "8800",
        "line": {
            "en": "'...M-...Morning Ageha.'"
        },
        "name": "Kotori"
    },
    {
        "id": "8c00",
        "line": {
            "en": "Kotori seems a little embarrassed as Ageha talks\\nto her."
        },
        "name": ""
    },
    {
        "id": "9000",
        "line": {
            "en": "'You got here first?'"
        },
        "name": "Aoi"
    },
    {
        "id": "9400",
        "line": {
            "en": "'Nope. I saw you guys racing along at top speed\\nand I followed you.'"
        },
        "name": "Ageha"
    },
    {
        "id": "9800",
        "line": {
            "en": "Oh? I didn't notice."
        },
        "name": ""
    },
    {
        "id": "9c00",
        "line": {
            "en": "'That's the first time I've seen someone running\\nand pushing a wheelchair.'"
        },
        "name": "Ageha"
    },
    {
        "id": "a000",
        "line": {
            "en": "'...Aoi, I'll go on ahead, okay?'"
        },
        "name": "Kotori"
    },
    {
        "id": "a400",
        "line": {
            "en": "Kotori was being careful around Ageha, and spoke\\nuncomfortably as she went on ahead."
        },
        "name": ""
    },
    {
        "id": "a800",
        "line": {
            "en": "Instead of being annoyed, she seemed more\\nembarrassed than anything."
        },
        "name": ""
    },
    {
        "id": "ac00",
        "line": {
            "en": "I think Ageha understands that too, but..."
        },
        "name": ""
    },
    {
        "id": "b000",
        "line": {
            "en": "'Aoi?'"
        },
        "name": "Ageha"
    },
    {
        "id": "b400",
        "line": {
            "en": "'...What?'"
        },
        "name": "Aoi"
    },
    {
        "id": "b800",
        "line": {
            "en": "'Oh, nothing. Well, I'm going ahead too.'"
        },
        "name": "Ageha"
    },
    {
        "id": "bc00",
        "line": {
            "en": "'See you, Aoi.'"
        },
        "name": "Ageha"
    },
    {
        "id": "c000",
        "line": {
            "en": "Seeming like she'd had enough of talking to me,\\nAgeha also went on ahead."
        },
        "name": ""
    },
    {
        "id": "c400",
        "line": {
            "en": "'Hey, wait, Ageha.'"
        },
        "name": "Aoi"
    },
    {
        "id": "c800",
        "line": {
            "en": "I chase after the two of them, and we head to the\\ngarage."
        },
        "name": ""
    },
    {
        "id": "cc00",
        "line": {
            "en": "'Wassup!'"
        },
        "name": "Aoi"
    },
    {
        "id": "d000",
        "line": {
            "en": "Amane was already inside the garage."
        },
        "name": ""
    },
    {
        "id": "d400",
        "line": {
            "en": "'...'"
        },
        "name": "Amane"
    },
    {
        "id": "d800",
        "line": {
            "en": "Amane was making a serious face in front of the\\ndrawing board."
        },
        "name": ""
    },
    {
        "id": "dc00",
        "line": {
            "en": "She's really concentrating, and hasn't noticed\\nus."
        },
        "name": ""
    },
    {
        "id": "e000",
        "line": {
            "en": "For a moment, I wasn't sure if I should call out\\nto her. But if we don't say anything, how many\\nhours would she be doing that?"
        },
        "name": ""
    },
    {
        "id": "e400",
        "line": {
            "en": "'Hi there, Amane!'"
        },
        "name": "Aoi"
    },
    {
        "id": "e800",
        "line": {
            "en": "'...?'"
        },
        "name": "Amane"
    },
    {
        "id": "ec00",
        "line": {
            "en": "'It's you guys...'"
        },
        "name": "Amane"
    },
    {
        "id": "f000",
        "line": {
            "en": "'Wassup, Amane?'"
        },
        "name": "Aoi"
    },
    {
        "id": "f400",
        "line": {
            "en": "'Wassup.'"
        },
        "name": "Ageha"
    },
    {
        "id": "f800",
        "line": {
            "en": "'W-...Wassup.'"
        },
        "name": "Kotori"
    },
    {
        "id": "fc00",
        "line": {
            "en": "Ageha and Kotori copy me."
        },
        "name": ""
    },
    {
        "id": "0100",
        "line": {
            "en": "'From now on, we'll do our best!'"
        },
        "name": "Aoi"
    },
    {
        "id": "0500",
        "line": {
            "en": "'Ah... umm...'"
        },
        "name": "Amane"
    },
    {
        "id": "0900",
        "line": {
            "en": "Amane points at me, and makes a troubled face."
        },
        "name": ""
    },
    {
        "id": "0d00",
        "line": {
            "en": "'You there, what's your name?'"
        },
        "name": "Amane"
    },
    {
        "id": "1100",
        "line": {
            "en": "That's right, I'd never once told her my name..."
        },
        "name": ""
    },
    {
        "id": "1500",
        "line": {
            "en": "Even though we've met several times."
        },
        "name": ""
    },
    {
        "id": "1900",
        "line": {
            "en": "'Aoi Minase, second year, class A!'"
        },
        "name": "Aoi"
    },
    {
        "id": "1d00",
        "line": {
            "en": "I give a very sharp self-introduction, and the\\nothers do likewise."
        },
        "name": ""
    },
    {
        "id": "2100",
        "line": {
            "en": "'Also from second year, Class A, Ageha Himegi!'"
        },
        "name": "Ageha"
    },
    {
        "id": "2500",
        "line": {
            "en": "'A-Also from second year, Class A, Kotori\\nHabane...'"
        },
        "name": "Kotori"
    },
    {
        "id": "2900",
        "line": {
            "en": "'Aoi... Ageha... Kotori... Aoi...\\nAgeha...Kotori...'"
        },
        "name": "Amane"
    },
    {
        "id": "2d00",
        "line": {
            "en": "She memorizes our faces, and names in order."
        },
        "name": ""
    },
    {
        "id": "3100",
        "line": {
            "en": "'I'm from fifth year, Class C... or was it D?\\n...Amane Mochizuki.'"
        },
        "name": "Amane"
    },
    {
        "id": "3500",
        "line": {
            "en": "She misses so many lessons that she apparently\\ndoesn't even know which class she's in."
        },
        "name": ""
    },
    {
        "id": "3900",
        "line": {
            "en": "'Thanks for yesterday. Because of you guys... I\\ncan continue to stay here.'"
        },
        "name": "Amane"
    },
    {
        "id": "3d00",
        "line": {
            "en": "We're somehow very grateful to hear these words\\nof thanks from Amane."
        },
        "name": ""
    },
    {
        "id": "4100",
        "line": {
            "en": "'Is it really alright for us to join?'"
        },
        "name": "Aoi"
    },
    {
        "id": "4500",
        "line": {
            "en": "She wasn't sure if she would accept new members."
        },
        "name": ""
    },
    {
        "id": "4900",
        "line": {
            "en": "Had she found the 'answer' she was looking for,\\nthen?"
        },
        "name": ""
    },
    {
        "id": "4d00",
        "line": {
            "en": "'Oh, yeah. You're all welcome.'"
        },
        "name": "Amane"
    },
    {
        "id": "5100",
        "line": {
            "en": "'Welcome to the Soaring Club.'"
        },
        "name": "Amane"
    },
    {
        "id": "5500",
        "line": {
            "en": "I don't know what she was worrying about, or how\\nshe arrived at her answer. But, it somehow seemed\\nthat there was no problem with us joining the\\nclub."
        },
        "name": ""
    },
    {
        "id": "5900",
        "line": {
            "en": "'Umm... Well then, let's do our best.'"
        },
        "name": "Amane"
    },
    {
        "id": "5d00",
        "line": {
            "en": "She said that like she was just throwing it out\\nthere, before returning to the drawing board."
        },
        "name": ""
    },
    {
        "id": "6100",
        "line": {
            "en": "She stares at the diagram with a serious look on\\nher face."
        },
        "name": ""
    },
    {
        "id": "6500",
        "line": {
            "en": "'Ah...'"
        },
        "name": "Aoi"
    },
    {
        "id": "6900",
        "line": {
            "en": "'...'"
        },
        "name": "Amane"
    },
    {
        "id": "6d00",
        "line": {
            "en": "'Amane?'"
        },
        "name": "Aoi"
    },
    {
        "id": "7100",
        "line": {
            "en": "'Hmm? Yes?'"
        },
        "name": "Amane"
    },
    {
        "id": "7500",
        "line": {
            "en": "'...What should we be doing?'"
        },
        "name": "Aoi"
    },
    {
        "id": "7900",
        "line": {
            "en": "'Oh, that's right. Make yourselves at home, have\\na cup of tea.'"
        },
        "name": "Amane"
    },
    {
        "id": "7d00",
        "line": {
            "en": "'There are some manga on that shelf too.'"
        },
        "name": "Amane"
    },
    {
        "id": "8100",
        "line": {
            "en": "On 'that shelf' was every volume of Slam Dunk."
        },
        "name": ""
    },
    {
        "id": "8500",
        "line": {
            "en": "The covers were faded, and it seemed like they'd\\nseen many years of 'service'."
        },
        "name": ""
    },
    {
        "id": "8900",
        "line": {
            "en": "'...'"
        },
        "name": "Ageha"
    },
    {
        "id": "8d00",
        "line": {
            "en": "'...'"
        },
        "name": "Kotori"
    },
    {
        "id": "9100",
        "line": {
            "en": "The two girls both make faces that say 'This\\nisn't what I thought it would be like."
        },
        "name": ""
    },
    {
        "id": "9500",
        "line": {
            "en": "My face might have been the same."
        },
        "name": ""
    },
    {
        "id": "9900",
        "line": {
            "en": "'Isn't there anything for us to do?'"
        },
        "name": "Kotori"
    },
    {
        "id": "9d00",
        "line": {
            "en": "'I told you, read some manga...'"
        },
        "name": "Amane"
    },
    {
        "id": "a100",
        "line": {
            "en": "'Not that, something to do with the glider!'"
        },
        "name": "Kotori"
    },
    {
        "id": "a500",
        "line": {
            "en": "'Huh...?'"
        },
        "name": "Amane"
    },
    {
        "id": "a900",
        "line": {
            "en": "'We really want to get involved with the glider!'"
        },
        "name": "Aoi"
    },
    {
        "id": "ad00",
        "line": {
            "en": "Amane opened her eyes wide."
        },
        "name": ""
    },
    {
        "id": "b100",
        "line": {
            "en": "'...Really? You guys are weird...'"
        },
        "name": "Amane"
    },
    {
        "id": "b500",
        "line": {
            "en": "I don't wanna hear that from you..."
        },
        "name": ""
    },
    {
        "id": "b900",
        "line": {
            "en": "'Um, Amane. Could it be that... we're in your\\nway? By joining the club?'"
        },
        "name": "Aoi"
    },
    {
        "id": "bd00",
        "line": {
            "en": "She didn't want anyone coming near this garage,\\ndid she?"
        },
        "name": ""
    },
    {
        "id": "c100",
        "line": {
            "en": "'No, that's not true! It's just... that...'"
        },
        "name": "Amane"
    },
    {
        "id": "c500",
        "line": {
            "en": "'I've been doing this by myself until now, so I\\ndon't know what you can do.'"
        },
        "name": "Amane"
    },
    {
        "id": "c900",
        "line": {
            "en": "When Amane was a step away from the national\\nchampionship with the Robotics Club, it seems she\\ndid most of it by herself."
        },
        "name": ""
    },
    {
        "id": "cd00",
        "line": {
            "en": "'(She's the type with no social skills.)'"
        },
        "name": "Kotori"
    },
    {
        "id": "d100",
        "line": {
            "en": "'(You're one to talk.)'"
        },
        "name": "Aoi"
    },
    {
        "id": "d500",
        "line": {
            "en": "'Excuse me, can I ask a question?'"
        },
        "name": "Ageha"
    },
    {
        "id": "d900",
        "line": {
            "en": "Ageha raised her hand."
        },
        "name": ""
    },
    {
        "id": "dd00",
        "line": {
            "en": "'Go ahead.'"
        },
        "name": "Amane"
    },
    {
        "id": "e100",
        "line": {
            "en": "'What activities are this club involved in,\\nspecifically?'"
        },
        "name": "Ageha"
    },
    {
        "id": "e500",
        "line": {
            "en": "Ageha asks a fundamental question."
        },
        "name": ""
    },
    {
        "id": "e900",
        "line": {
            "en": "I feel like she's been asked a similar question\\nbefore, but then, she was only asked for a\\nsummary."
        },
        "name": ""
    },
    {
        "id": "ed00",
        "line": {
            "en": "If we're actually going to take part in this\\nclub, we need more specific information."
        },
        "name": ""
    },
    {
        "id": "f100",
        "line": {
            "en": "'Well, ah... We make gliders and fly.'"
        },
        "name": "Amane"
    },
    {
        "id": "f500",
        "line": {
            "en": "That's it."
        },
        "name": ""
    },
    {
        "id": "f900",
        "line": {
            "en": "I think everyone knows that already."
        },
        "name": ""
    },
    {
        "id": "fd00",
        "line": {
            "en": "'Making or flying, which is the main objective?'"
        },
        "name": "Ageha"
    },
    {
        "id": "0200",
        "line": {
            "en": "'...After building it, then you'd fly it. Isn't\\nthat what normally happens?'"
        },
        "name": "Kotori"
    },
    {
        "id": "0600",
        "line": {
            "en": "'But you're not aiming to enter competitions, or\\nanything, are you?'"
        },
        "name": "Aoi"
    },
    {
        "id": "0a00",
        "line": {
            "en": "'No, I'm not.'"
        },
        "name": "Amane"
    },
    {
        "id": "0e00",
        "line": {
            "en": "She answered bluntly, and without even a shred of\\ninterest."
        },
        "name": ""
    },
    {
        "id": "1200",
        "line": {
            "en": "'So, the main objective is to build it then?'"
        },
        "name": "Ageha"
    },
    {
        "id": "1600",
        "line": {
            "en": "'No, that's wrong. Flying above the clouds is the\\nobjective, right?'"
        },
        "name": "Kotori"
    },
    {
        "id": "1a00",
        "line": {
            "en": "Amane somehow lacks confidence when she nods."
        },
        "name": ""
    },
    {
        "id": "1e00",
        "line": {
            "en": "'How far have you gotten with the glider?'"
        },
        "name": "Ageha"
    },
    {
        "id": "2200",
        "line": {
            "en": "'A few days ago, I finally finished assembling it\\nand went for a test flight, but...'"
        },
        "name": "Amane"
    },
    {
        "id": "2600",
        "line": {
            "en": "As Amane explains, she moves into the garage."
        },
        "name": ""
    },
    {
        "id": "2a00",
        "line": {
            "en": "'The main wings snapped.'"
        },
        "name": "Amane"
    },
    {
        "id": "2e00",
        "line": {
            "en": "In the corner of the garage lay the broken wings."
        },
        "name": ""
    },
    {
        "id": "3200",
        "line": {
            "en": "'It looks like they weren't strong enough. Now,\\nI'm reviewing the designs, but...'"
        },
        "name": "Amane"
    },
    {
        "id": "3600",
        "line": {
            "en": "Looking at the twisted wings, Amane lets out a\\nlittle groan."
        },
        "name": ""
    },
    {
        "id": "3a00",
        "line": {
            "en": "'I've redone the strength calculations, but this\\ntime, I can't find where the problem is.'"
        },
        "name": "Amane"
    },
    {
        "id": "3e00",
        "line": {
            "en": "'I don't know why this happened, so it's a\\nproblem...'"
        },
        "name": "Amane"
    },
    {
        "id": "4200",
        "line": {
            "en": "If Amane doesn't understand, there's no way we\\nwill."
        },
        "name": ""
    },
    {
        "id": "4600",
        "line": {
            "en": "I thought to myself as Ageha moved close to\\nAmane, and checked the broken parts of the main\\nwings."
        },
        "name": ""
    },
    {
        "id": "4a00",
        "line": {
            "en": "Then..."
        },
        "name": ""
    },
    {
        "id": "4e00",
        "line": {
            "en": "'Yep, this'll snap,'"
        },
        "name": "Ageha"
    },
    {
        "id": "5200",
        "line": {
            "en": "she stated simply."
        },
        "name": ""
    },
    {
        "id": "5600",
        "line": {
            "en": "'How do you know that??'"
        },
        "name": "Amane"
    },
    {
        "id": "5a00",
        "line": {
            "en": "'See here...? The thickness is uneven, and it's\\ndistorted in places.'"
        },
        "name": "Ageha"
    },
    {
        "id": "5e00",
        "line": {
            "en": "'Oh yeah, it is...'"
        },
        "name": "Amane"
    },
    {
        "id": "6200",
        "line": {
            "en": "'The construction methods are too rough. The\\njoints couldn't withstand the load and it\\ncracked.'"
        },
        "name": "Ageha"
    },
    {
        "id": "6600",
        "line": {
            "en": "Amane reels in shock."
        },
        "name": ""
    },
    {
        "id": "6a00",
        "line": {
            "en": "'Is that what it was...?'"
        },
        "name": "Amane"
    },
    {
        "id": "6e00",
        "line": {
            "en": "And then..."
        },
        "name": ""
    },
    {
        "id": "7200",
        "line": {
            "en": "'It's because I'm not very good with my hands...'"
        },
        "name": "Amane"
    },
    {
        "id": "7600",
        "line": {
            "en": "She becomes timid."
        },
        "name": ""
    },
    {
        "id": "7a00",
        "line": {
            "en": "'You made this by hand, piece by piece?'"
        },
        "name": "Aoi"
    },
    {
        "id": "7e00",
        "line": {
            "en": "'I didn't do it all myself, but... The fuselage\\nis handmade.'"
        },
        "name": "Amane"
    },
    {
        "id": "8200",
        "line": {
            "en": "'...This... is handmade?'"
        },
        "name": "Kotori"
    },
    {
        "id": "8600",
        "line": {
            "en": "Kotori and I were pretty surprised by this, but\\nAgeha didn't seem to make much of a big deal\\nabout it."
        },
        "name": ""
    },
    {
        "id": "8a00",
        "line": {
            "en": "'It's too rough... It's too rough...'"
        },
        "name": "Amane"
    },
    {
        "id": "8e00",
        "line": {
            "en": "This is bad, she's totally depressed."
        },
        "name": ""
    },
    {
        "id": "9200",
        "line": {
            "en": "'Because of the parts Aoi got, I was able to fix\\nthe malfunction in the instruments.'"
        },
        "name": "Amane"
    },
    {
        "id": "9600",
        "line": {
            "en": "'If I can just get the main wings repaired, it\\ncan go on another test flight.'"
        },
        "name": "Amane"
    },
    {
        "id": "9a00",
        "line": {
            "en": "'Are you going to do the wing repairs by hand\\ntoo?'"
        },
        "name": "Aoi"
    },
    {
        "id": "9e00",
        "line": {
            "en": "'Yeah, of course.'"
        },
        "name": "Amane"
    },
    {
        "id": "a200",
        "line": {
            "en": "Ageha takes a part of the wing that isn't\\nsnapped, and looks it over, with a troubled look\\non her face."
        },
        "name": ""
    },
    {
        "id": "a600",
        "line": {
            "en": "'Wouldn't it be better to rebuild the wings from\\nscratch?'"
        },
        "name": "Ageha"
    },
    {
        "id": "aa00",
        "line": {
            "en": "'If you don't, then other parts might snap too,\\ny'know.'"
        },
        "name": "Ageha"
    },
    {
        "id": "ae00",
        "line": {
            "en": "'Sniffle sniffle...'"
        },
        "name": "Amane"
    },
    {
        "id": "b200",
        "line": {
            "en": "Amane looks like she's about to cry."
        },
        "name": ""
    },
    {
        "id": "b600",
        "line": {
            "en": "'Alright then, we'll help.'"
        },
        "name": "Aoi"
    },
    {
        "id": "ba00",
        "line": {
            "en": "'This is fiber-reinforced plastic, right? I've\\nworked with this before. I might be able to do\\nsomething with this.'"
        },
        "name": "Ageha"
    },
    {
        "id": "be00",
        "line": {
            "en": "'We should start right away. That way, we can fly\\nit sooner, right?'"
        },
        "name": "Kotori"
    },
    {
        "id": "c200",
        "line": {
            "en": "The three new members' motivation has returned,\\nand now we're getting excited."
        },
        "name": ""
    },
    {
        "id": "c600",
        "line": {
            "en": "'I really want to do that too. But,\\nunfortunately, there aren't any materials.'"
        },
        "name": "Amane"
    },
    {
        "id": "ca00",
        "line": {
            "en": "'There are lots of parts that can be used for\\nrepairs...'"
        },
        "name": "Amane"
    },
    {
        "id": "ce00",
        "line": {
            "en": "'To make something of this size from scratch\\nwould require a large amount.'"
        },
        "name": "Ageha"
    },
    {
        "id": "d200",
        "line": {
            "en": "'How do you usually get things like that?'"
        },
        "name": "Ageha"
    },
    {
        "id": "d600",
        "line": {
            "en": "'Mail order.'"
        },
        "name": "Amane"
    },
    {
        "id": "da00",
        "line": {
            "en": "Amane goes to the laptop and navigates to the\\nwebsite that sells her materials."
        },
        "name": ""
    },
    {
        "id": "de00",
        "line": {
            "en": "'To remake the main wings, we'd need about this\\nmuch,'"
        },
        "name": "Amane"
    },
    {
        "id": "e200",
        "line": {
            "en": "said Amane as she entered a number."
        },
        "name": ""
    },
    {
        "id": "e600",
        "line": {
            "en": "'Ack! That's not a bad price, but there's no way\\nwe can afford it on the club's budget...'"
        },
        "name": "Ageha"
    },
    {
        "id": "ea00",
        "line": {
            "en": "I don't know how much the budget is for the\\nSoaring Club, but the price displayed on the mail\\norder site was no small amount."
        },
        "name": ""
    },
    {
        "id": "ee00",
        "line": {
            "en": "'Hmm. Well, that's no problem.'"
        },
        "name": "Amane"
    },
    {
        "id": "f200",
        "line": {
            "en": "Click."
        },
        "name": ""
    },
    {
        "id": "f600",
        "line": {
            "en": "Amane submitted the order."
        },
        "name": ""
    },
    {
        "id": "fa00",
        "line": {
            "en": "'Is that okay, Amane?'"
        },
        "name": "Ageha"
    },
    {
        "id": "fe00",
        "line": {
            "en": "'Hmm? Yeah, that amount of money should be no\\nproblem at all.'"
        },
        "name": "Amane"
    },
    {
        "id": "0300",
        "line": {
            "en": "Whaddya mean, 'no problem'? Could it be that when\\nit comes to the club budgets, the Soaring Club\\ngets preferential treatment?"
        },
        "name": ""
    },
    {
        "id": "0700",
        "line": {
            "en": "'It'll take a little while for it to arrive. Then\\nwe can get started.'"
        },
        "name": "Ageha"
    },
    {
        "id": "0b00",
        "line": {
            "en": "Which means that we don't have anything to do\\nnow, after all."
        },
        "name": ""
    },
    {
        "id": "0f00",
        "line": {
            "en": "'Until then, what should we do?'"
        },
        "name": "Kotori"
    },
    {
        "id": "1300",
        "line": {
            "en": "'...Read some manga or something.'"
        },
        "name": "Amane"
    },
    {
        "id": "1700",
        "line": {
            "en": "With that order, the Soaring Club President went\\nback to staring at the designs she was working\\non."
        },
        "name": ""
    },
    {
        "id": "1b00",
        "line": {
            "en": "Even if we say we've got nothing to do, it's not\\nlike there's nothing whatsoever for us to do."
        },
        "name": ""
    },
    {
        "id": "1f00",
        "line": {
            "en": "We were still beginners when it came to gliders,\\nso we took some books from the shelf and started\\nour own little study session."
        },
        "name": ""
    },
    {
        "id": "2300",
        "line": {
            "en": "Aerodynamics, glider construction, and so on."
        },
        "name": ""
    },
    {
        "id": "2700",
        "line": {
            "en": "As for the basics on how aircraft fly, we were\\ntold that before by Amane."
        },
        "name": ""
    },
    {
        "id": "2b00",
        "line": {
            "en": "In terms of the various methods of creating what\\nis known as 'lift', the more we found out, the\\nmore interesting it became."
        },
        "name": ""
    },
    {
        "id": "2f00",
        "line": {
            "en": "And then, it was noon..."
        },
        "name": ""
    },
    {
        "id": "3300",
        "line": {
            "en": "'Mmmmm, that's tasty! That was the first intake\\nof calories I've had in a while!'"
        },
        "name": "Amane"
    },
    {
        "id": "3700",
        "line": {
            "en": "Amane was already enjoying the bread and rice\\nballs that Kotori and I bought at the convenience\\nstore this morning."
        },
        "name": ""
    },
    {
        "id": "3b00",
        "line": {
            "en": "'Just wondering: How long has it been since you\\nlast ate?'"
        },
        "name": "Aoi"
    },
    {
        "id": "3f00",
        "line": {
            "en": "'Hmm... 46 hours ago. That time, it was a pork\\ncutlet bowl from the cafeteria! I had a big\\nbowl!'"
        },
        "name": "Amane"
    },
    {
        "id": "4300",
        "line": {
            "en": "'Would you like to eat this too...?'"
        },
        "name": "Kotori"
    },
    {
        "id": "4700",
        "line": {
            "en": "Out of pity, Kotori offered Amane her pickled\\nplum rice ball."
        },
        "name": ""
    },
    {
        "id": "4b00",
        "line": {
            "en": "'Oh, thanks.'"
        },
        "name": "Amane"
    },
    {
        "id": "4f00",
        "line": {
            "en": "'She has quite an appetite, doesn't she?'"
        },
        "name": "Ageha"
    },
    {
        "id": "5300",
        "line": {
            "en": "Witnessing the 'Amane Mochizuki style eating\\ntechnique' for the first time, Ageha is, as\\nexpected, pretty freaked out."
        },
        "name": ""
    },
    {
        "id": "5700",
        "line": {
            "en": "It could be because the image of the 'beautiful\\nand mysterious senpai' that Ageha had been\\nholding onto was being completely annihilated."
        },
        "name": ""
    },
    {
        "id": "5b00",
        "line": {
            "en": "By the way, because we had club activities this\\nmorning, Ageha brought a lunchbox."
        },
        "name": ""
    },
    {
        "id": "5f00",
        "line": {
            "en": "'Are there any other parts we need?'"
        },
        "name": "Aoi"
    },
    {
        "id": "6300",
        "line": {
            "en": "I asked Amane once she had calmed down after her\\nmeal."
        },
        "name": ""
    },
    {
        "id": "6700",
        "line": {
            "en": "'Hmm...'"
        },
        "name": "Amane"
    },
    {
        "id": "6b00",
        "line": {
            "en": "'Only one.'"
        },
        "name": "Amane"
    },
    {
        "id": "6f00",
        "line": {
            "en": "'What is it?'"
        },
        "name": "Ageha"
    },
    {
        "id": "7300",
        "line": {
            "en": "'I can't get one no matter what I do. The truth\\nis, it's a big problem.'"
        },
        "name": "Amane"
    },
    {
        "id": "7700",
        "line": {
            "en": "From the way she said it, we all crowd around to\\nlisten intently to her story."
        },
        "name": ""
    },
    {
        "id": "7b00",
        "line": {
            "en": "'What is it you need?'"
        },
        "name": "Kotori"
    },
    {
        "id": "7f00",
        "line": {
            "en": "'A pilot.'"
        },
        "name": "Amane"
    },
    {
        "id": "8300",
        "line": {
            "en": "Shing!"
        },
        "name": ""
    },
    {
        "id": "8700",
        "line": {
            "en": "When Amane said this, she made a dramatic face\\nshe would use if this were on TV, looking\\nstraight at the camera."
        },
        "name": ""
    },
    {
        "id": "8b00",
        "line": {
            "en": "'Aren't you going to fly it?'"
        },
        "name": "Aoi"
    },
    {
        "id": "8f00",
        "line": {
            "en": "'You flew it the other day!'"
        },
        "name": "Kotori"
    },
    {
        "id": "9300",
        "line": {
            "en": "'I'm not very good though. Also, last time, I\\nalmost botched the landing, and damaged the\\ntail.'"
        },
        "name": "Amane"
    },
    {
        "id": "9700",
        "line": {
            "en": "'It's true. The tail has scratches on it.'"
        },
        "name": "Ageha"
    },
    {
        "id": "9b00",
        "line": {
            "en": "'I don't have much confidence in my motor\\nskills.'"
        },
        "name": "Amane"
    },
    {
        "id": "9f00",
        "line": {
            "en": "'...Hang on, could you come here for a second?'"
        },
        "name": "Aoi"
    },
    {
        "id": "a300",
        "line": {
            "en": "I call Amane over to an open space."
        },
        "name": ""
    },
    {
        "id": "a700",
        "line": {
            "en": "'Please try to do some repeated side jumps.'"
        },
        "name": "Aoi"
    },
    {
        "id": "ab00",
        "line": {
            "en": "'Oh, okay.'"
        },
        "name": "Amane"
    },
    {
        "id": "af00",
        "line": {
            "en": "Amane tried some repeated side jumps, like I\\nasked."
        },
        "name": ""
    },
    {
        "id": "b300",
        "line": {
            "en": "'Hup, haa, hup...haa...'"
        },
        "name": "Amane"
    },
    {
        "id": "b700",
        "line": {
            "en": "'Amane, it's repeated side jumps, y'know?'"
        },
        "name": "Kotori"
    },
    {
        "id": "bb00",
        "line": {
            "en": "'Y-... Yeah, I know! Hup, haa... ugh... whoa...'"
        },
        "name": "Amane"
    },
    {
        "id": "bf00",
        "line": {
            "en": "It's supposed to be repeated side jumps, but each\\ntime, the distance is different and sometimes she\\nturns her body."
        },
        "name": ""
    },
    {
        "id": "c300",
        "line": {
            "en": "It should be just moving quickly from side to\\nside, but it looks like some kind of horrific\\ndancing."
        },
        "name": ""
    },
    {
        "id": "c700",
        "line": {
            "en": "'It's true, she's terrible...!'"
        },
        "name": "Aoi, Kotori, Ageha"
    },
    {
        "id": "cb00",
        "line": {
            "en": "Without thinking, we all murmured in unison."
        },
        "name": ""
    },
    {
        "id": "cf00",
        "line": {
            "en": "It didn't seem that motor skills were that\\nimportant for piloting a glider, but that level\\nof clumsiness could make things pretty dangerous."
        },
        "name": ""
    },
    {
        "id": "d300",
        "line": {
            "en": "'Also... hup, haa... I have acrophobia.'"
        },
        "name": "Amane"
    },
    {
        "id": "d700",
        "line": {
            "en": "'Huh...?'"
        },
        "name": "Ageha"
    },
    {
        "id": "db00",
        "line": {
            "en": "'When I go to high places, I get scared and feel\\ndizzy.'"
        },
        "name": "Amane"
    },
    {
        "id": "df00",
        "line": {
            "en": "Then why the hell is she making a glider?"
        },
        "name": ""
    },
    {
        "id": "e300",
        "line": {
            "en": "'But I'm qualified. You only need one document.'"
        },
        "name": "Amane"
    },
    {
        "id": "e700",
        "line": {
            "en": "In other words, she's been trying really hard."
        },
        "name": ""
    },
    {
        "id": "eb00",
        "line": {
            "en": "'Oh, that's enough of the repeated side jumps.'"
        },
        "name": "Aoi"
    },
    {
        "id": "ef00",
        "line": {
            "en": "'Phew... I'm worn out.'"
        },
        "name": "Amane"
    },
    {
        "id": "f300",
        "line": {
            "en": "Amane wipes the sweat from her forehead. She's a\\nbeautiful girl, so at least she's able to do\\nthose kinds of movements well."
        },
        "name": ""
    },
    {
        "id": "f700",
        "line": {
            "en": "'Me, me, me!'"
        },
        "name": "Kotori"
    },
    {
        "id": "fb00",
        "line": {
            "en": "Suddenly, Kotori raised her hand."
        },
        "name": ""
    },
    {
        "id": "ff00",
        "line": {
            "en": "'I want to do it! I want to be the pilot!'"
        },
        "name": "Kotori"
    },
    {
        "id": "0004",
        "line": {
            "en": "As Kotori vigorously volunteered, Amane made a\\ntroubled face."
        },
        "name": ""
    },
    {
        "id": "0404",
        "line": {
            "en": "'...I'm sorry, but you can't do it.'"
        },
        "name": "Amane"
    },
    {
        "id": "0804",
        "line": {
            "en": "'Why not...?' If I need to practice, I'll try\\nreally hard. I might not look like it, but I've\\ngot great motor skills.'"
        },
        "name": "Kotori"
    },
    {
        "id": "0c04",
        "line": {
            "en": "'You can't push the rudder pedal though, can\\nyou?'"
        },
        "name": "Amane"
    },
    {
        "id": "1004",
        "line": {
            "en": "'Rudder pedal...?'"
        },
        "name": "Kotori"
    },
    {
        "id": "1404",
        "line": {
            "en": "There are pedals in the cockpit."
        },
        "name": ""
    },
    {
        "id": "1804",
        "line": {
            "en": "If you can't push them, you can't pilot it."
        },
        "name": ""
    },
    {
        "id": "1c04",
        "line": {
            "en": "Kotori moved back, dejected."
        },
        "name": ""
    },
    {
        "id": "2004",
        "line": {
            "en": "'Well, I'd rather not do it. I'm more interested\\nin making it than flying.'"
        },
        "name": "Ageha"
    },
    {
        "id": "2404",
        "line": {
            "en": "Ageha, who is looking inside the aircraft's\\ncockpit, sounds like she's talking about someone\\nelse."
        },
        "name": ""
    },
    {
        "id": "2804",
        "line": {
            "en": "That leaves one person."
        },
        "name": ""
    },
    {
        "id": "2c04",
        "line": {
            "en": "'I wanna do it.'"
        },
        "name": "Aoi"
    },
    {
        "id": "3004",
        "line": {
            "en": "If it's motor skills we're talking about, I'm\\nfairly confident."
        },
        "name": ""
    },
    {
        "id": "3404",
        "line": {
            "en": "'Alright, it's decided. Aoi, you will undergo\\ntraining to become the pilot.'"
        },
        "name": "Amane"
    },
    {
        "id": "3804",
        "line": {
            "en": "'Yes!'"
        },
        "name": "Aoi"
    },
    {
        "id": "3c04",
        "line": {
            "en": "And that's how I suddenly became the pilot."
        },
        "name": ""
    },
    {
        "id": "4004",
        "line": {
            "en": "After club activities were over, I returned to\\nthe dorm."
        },
        "name": ""
    },
    {
        "id": "4404",
        "line": {
            "en": "'C'mon, cheer up.'"
        },
        "name": "Aoi"
    },
    {
        "id": "4804",
        "line": {
            "en": "'What? I am cheerful.'"
        },
        "name": "Kotori"
    },
    {
        "id": "4c04",
        "line": {
            "en": "Ever since it was decided that I'd be the pilot,\\nKotori's been feeling down."
        },
        "name": ""
    },
    {
        "id": "5004",
        "line": {
            "en": "'Just because you can't pilot it, doesn't mean\\nyou can't fly.'"
        },
        "name": "Aoi"
    },
    {
        "id": "5404",
        "line": {
            "en": "That glider is a double-seater."
        },
        "name": ""
    },
    {
        "id": "5804",
        "line": {
            "en": "There are two types of glider cockpit,\\nsingle-seater and double-seater."
        },
        "name": ""
    },
    {
        "id": "5c04",
        "line": {
            "en": "Obviously, the single-seater fits one person,\\nwhile the double-seater fits two."
        },
        "name": ""
    },
    {
        "id": "6004",
        "line": {
            "en": "'Once I'm able to fly, you're the first person\\nI'm taking with me.'"
        },
        "name": "Aoi"
    },
    {
        "id": "6404",
        "line": {
            "en": "'It's irritating how it feels like you're looking\\ndown on me...'"
        },
        "name": "Kotori"
    },
    {
        "id": "6804",
        "line": {
            "en": "'...but, I'll settle for that.'"
        },
        "name": "Kotori"
    },
    {
        "id": "6c04",
        "line": {
            "en": "'Good. Alright, let's get ready for dinner.'"
        },
        "name": "Aoi"
    },
    {
        "id": "7004",
        "line": {
            "en": "'Hello, we're back!'"
        },
        "name": "Aoi"
    },
    {
        "id": "7404",
        "line": {
            "en": "I push the wheelchair through the doorway."
        },
        "name": ""
    },
    {
        "id": "7804",
        "line": {
            "en": "'Welcome back, Aoi, Kotori-chan!'"
        },
        "name": "Kanako"
    },
    {
        "id": "7c04",
        "line": {
            "en": "'Hello.'"
        },
        "name": "Kotori"
    },
    {
        "id": "8004",
        "line": {
            "en": "'Kanako, thanks so much for yesterday.'"
        },
        "name": "Aoi"
    },
    {
        "id": "8404",
        "line": {
            "en": "'No, no, I'm glad it went well. I wanted to soar\\nto the heavens too, though...'"
        },
        "name": "Kanako"
    },
    {
        "id": "8804",
        "line": {
            "en": "'By the way, Kotori, she's here.'"
        },
        "name": "Kanako"
    },
    {
        "id": "8c04",
        "line": {
            "en": "'?'"
        },
        "name": "Kotori"
    },
    {
        "id": "9004",
        "line": {
            "en": "'Kotori-chaaaaaaaaaaaan!!!!!!!!'"
        },
        "name": "Woman"
    },
    {
        "id": "9404",
        "line": {
            "en": "Fwoosh!"
        },
        "name": ""
    },
    {
        "id": "9804",
        "line": {
            "en": "'Aargh!'"
        },
        "name": "Kotori"
    },
    {
        "id": "9c04",
        "line": {
            "en": "As we entered the dining hall, with the force of\\nthe Saint Bernard from the other day, an unknown\\ngirl came flying out to hug Kotori."
        },
        "name": ""
    },
    {
        "id": "a004",
        "line": {
            "en": "'S-...Sis...!'"
        },
        "name": "Kotori"
    },
    {
        "id": "a404",
        "line": {
            "en": "'I'm sorryyyyy!! I'm sorry that I couldn't come\\nback to see yoooou!!!'"
        },
        "name": "Kotori's older sister"
    },
    {
        "id": "a804",
        "line": {
            "en": "Kotori's big sister burst into tears as she held\\nher and rubbed her cheeks against hers."
        },
        "name": ""
    },
    {
        "id": "ac04",
        "line": {
            "en": "'Hold on... uh... that... that hurts! Hibari...\\nlet go!'"
        },
        "name": "Kotori"
    },
    {
        "id": "b004",
        "line": {
            "en": "'Okay... sniffle.'"
        },
        "name": "Hibari"
    },
    {
        "id": "b404",
        "line": {
            "en": "Realizing that she was suffocating her little\\nsister, she let go of Kotori."
        },
        "name": ""
    },
    {
        "id": "b804",
        "line": {
            "en": "'Who's she?'"
        },
        "name": "Aoi"
    },
    {
        "id": "bc04",
        "line": {
            "en": "'She's my big sister...'"
        },
        "name": "Kotori"
    },
    {
        "id": "c004",
        "line": {
            "en": "Kotori introduced us brusquely in a way that\\nimplied, 'I don't like doing introductions."
        },
        "name": ""
    },
    {
        "id": "c404",
        "line": {
            "en": "'Sis, this mean-looking boy is... well, he\\ndoesn't really look that mean but he's violent\\nand karate chops me...'"
        },
        "name": "Kotori"
    },
    {
        "id": "c804",
        "line": {
            "en": "'Yeah, yeah, hurry up with the introduction.'"
        },
        "name": "Aoi"
    },
    {
        "id": "cc04",
        "line": {
            "en": "'He's our new dorm mother.'"
        },
        "name": "Kotori"
    },
    {
        "id": "d004",
        "line": {
            "en": "'Nice to meet you, I'm Aoi Minase, the current\\ndorm manager.'"
        },
        "name": "Aoi"
    },
    {
        "id": "d404",
        "line": {
            "en": "I bowed my head, and Kotori's sister quickly\\nstood up, and straightened out her messed up\\nclothes."
        },
        "name": ""
    },
    {
        "id": "d804",
        "line": {
            "en": "'Sorry for the late introduction, I'm Hibari\\nHabane. Kotori's older sister.'"
        },
        "name": "Hibari"
    },
    {
        "id": "dc04",
        "line": {
            "en": "She seems very proud to say that she's Kotori's\\nolder sister."
        },
        "name": ""
    },
    {
        "id": "e004",
        "line": {
            "en": "'I heard there was a new dorm mother, so I\\nthought I should meet you as soon as possible.'"
        },
        "name": "Hibari"
    },
    {
        "id": "e404",
        "line": {
            "en": "'But I've been away from Japan due to my job for\\na while...'"
        },
        "name": "Hibari"
    },
    {
        "id": "e804",
        "line": {
            "en": "'This is nothing special, but please share it\\nwith everyone.'"
        },
        "name": "Hibari"
    },
    {
        "id": "ec04",
        "line": {
            "en": "She gave me a deep bow, and passed me something\\nin the wrapper of a famous Japanese sweets shop."
        },
        "name": ""
    },
    {
        "id": "f004",
        "line": {
            "en": "'Thank you very much.'"
        },
        "name": "Aoi"
    },
    {
        "id": "f404",
        "line": {
            "en": "I was surprised at first, but she seems like a\\nperfectly sensible person."
        },
        "name": ""
    },
    {
        "id": "f804",
        "line": {
            "en": "She's gentle and seems like a nice... a little\\ndifferent from her little sister."
        },
        "name": ""
    },
    {
        "id": "fc04",
        "line": {
            "en": "'What did you buy?'"
        },
        "name": "Kotori"
    },
    {
        "id": "0104",
        "line": {
            "en": "'Sweet bean jelly from Mifune. Also, there's some\\nice cream in the fridge.'"
        },
        "name": "Hibari"
    },
    {
        "id": "0504",
        "line": {
            "en": "'Alright! As expected of my big sis!'"
        },
        "name": "Kotori"
    },
    {
        "id": "0904",
        "line": {
            "en": "Kotori rushes straight to the fridge."
        },
        "name": ""
    },
    {
        "id": "0d04",
        "line": {
            "en": "'You can eat that after dinner!'"
        },
        "name": "Aoi"
    },
    {
        "id": "1104",
        "line": {
            "en": "'It's fine, just one spoonful!'"
        },
        "name": "Kotori"
    },
    {
        "id": "1504",
        "line": {
            "en": "'No.'"
        },
        "name": "Aoi"
    },
    {
        "id": "1904",
        "line": {
            "en": "'Tch... mean as always.'"
        },
        "name": "Kotori"
    },
    {
        "id": "1d04",
        "line": {
            "en": "'Ha ha ha, Kotori looks like she's having such a\\ngood time! I had no reason to worry...'"
        },
        "name": "Hibari"
    },
    {
        "id": "2104",
        "line": {
            "en": "'...'"
        },
        "name": "Hibari"
    },
    {
        "id": "2504",
        "line": {
            "en": "'Oh, that's right, Kotori!!'"
        },
        "name": "Hibari"
    },
    {
        "id": "2904",
        "line": {
            "en": "While Kotori had the fridge open and was\\nrummaging around inside, her sister went over to\\nher."
        },
        "name": ""
    },
    {
        "id": "2d04",
        "line": {
            "en": "'I was so happy to see you that I completely\\nforgot!'"
        },
        "name": "Hibari"
    },
    {
        "id": "3104",
        "line": {
            "en": "'Are you serious about quitting school!?'"
        },
        "name": "Hibari"
    },
    {
        "id": "3504",
        "line": {
            "en": "'Not so loud!!'"
        },
        "name": "Kotori"
    },
    {
        "id": "3904",
        "line": {
            "en": "There are other boarders outside the dining hall."
        },
        "name": ""
    },
    {
        "id": "3d04",
        "line": {
            "en": "'Why do you want to quit? Did something bad\\nhappen?'"
        },
        "name": "Hibari"
    },
    {
        "id": "4104",
        "line": {
            "en": "'If so, I'll speak to your teacher...'"
        },
        "name": "Hibari"
    },
    {
        "id": "4504",
        "line": {
            "en": "'I'm not going to quit anymore.'"
        },
        "name": "Kotori"
    },
    {
        "id": "4904",
        "line": {
            "en": "'Huh...?'"
        },
        "name": "Hibari"
    },
    {
        "id": "4d04",
        "line": {
            "en": "'...I still haven't completely made up my mind,\\nthough. I'm going to keep trying for a little\\nwhile longer.'"
        },
        "name": "Kotori"
    },
    {
        "id": "5104",
        "line": {
            "en": "'I see...'"
        },
        "name": "Hibari"
    },
    {
        "id": "5504",
        "line": {
            "en": "Hibari breathes a sigh of relief."
        },
        "name": ""
    },
    {
        "id": "5904",
        "line": {
            "en": "'Kotori, when you said you wanted to quit school,\\nwhile I was away, I kept worrying and\\nworrying...'"
        },
        "name": "Hibari"
    },
    {
        "id": "5d04",
        "line": {
            "en": "'I'm sorry for worrying you like that.'"
        },
        "name": "Kotori"
    },
    {
        "id": "6104",
        "line": {
            "en": "'No, that's okay...'"
        },
        "name": "Hibari"
    },
    {
        "id": "6504",
        "line": {
            "en": "Oh yeah, she said just now that she was working\\naway from Japan."
        },
        "name": ""
    },
    {
        "id": "6904",
        "line": {
            "en": "Kanako said before that her sister hadn't been\\nhere for a while, but that was why?"
        },
        "name": ""
    },
    {
        "id": "6d04",
        "line": {
            "en": "'Where did you go?'"
        },
        "name": "Aoi"
    },
    {
        "id": "7104",
        "line": {
            "en": "'On an overseas business trip. She's fluent in\\nGerman, Spanish, and Swedish.'"
        },
        "name": "Kotori"
    },
    {
        "id": "7504",
        "line": {
            "en": "I don't really get it, but that's amazing!"
        },
        "name": ""
    },
    {
        "id": "7904",
        "line": {
            "en": "'I was against it, but the company ordered me to\\ndo it...'"
        },
        "name": "Hibari"
    },
    {
        "id": "7d04",
        "line": {
            "en": "'She was only studying foreign languages as a\\nhobby.'"
        },
        "name": "Kotori"
    },
    {
        "id": "8104",
        "line": {
            "en": "'If it meant that I couldn't see Kotori, I\\nthought that it might be better to quit the\\ncompany.'"
        },
        "name": "Hibari"
    },
    {
        "id": "8504",
        "line": {
            "en": "'No, that would be going too far, sis...'"
        },
        "name": "Kotori"
    },
    {
        "id": "8904",
        "line": {
            "en": "'No, not really.'"
        },
        "name": "Hibari"
    },
    {
        "id": "8d04",
        "line": {
            "en": "'Actually I was supposed to be back tomorrow, but\\nI was so worried that I was at my wit's end and\\ncame back a day early!'"
        },
        "name": "Hibari"
    },
    {
        "id": "9104",
        "line": {
            "en": "she said while clinging onto Kotori."
        },
        "name": ""
    },
    {
        "id": "9504",
        "line": {
            "en": "'So, what really happened? Tell me everything!'"
        },
        "name": "Hibari"
    },
    {
        "id": "9904",
        "line": {
            "en": "'I-...It's fine now. It's no big deal, it was\\nlike the 'May blues' that people usually get a\\nmonth after the start of the school year, but it\\ncame two months late.'"
        },
        "name": "Kotori"
    },
    {
        "id": "9d04",
        "line": {
            "en": "'Sniffle'"
        },
        "name": "Hibari"
    },
    {
        "id": "a104",
        "line": {
            "en": "Hibari looked at me with tearful eyes."
        },
        "name": ""
    },
    {
        "id": "a504",
        "line": {
            "en": "She was trying to say that if I knew anything, I\\nshould spill the beans."
        },
        "name": ""
    },
    {
        "id": "a904",
        "line": {
            "en": "'Umm... I think that everything's okay with\\nKotori.'"
        },
        "name": "Aoi"
    },
    {
        "id": "ad04",
        "line": {
            "en": "'Today, she went to do club activities even\\nthough we had a day off from school.'"
        },
        "name": "Aoi"
    },
    {
        "id": "b104",
        "line": {
            "en": "'Club activities?'"
        },
        "name": "Hibari"
    },
    {
        "id": "b504",
        "line": {
            "en": "'We're in the Soaring Club. Right, Kotori?'"
        },
        "name": "Aoi"
    },
    {
        "id": "b904",
        "line": {
            "en": "'Soaring Club? What's that?'"
        },
        "name": "Hibari"
    },
    {
        "id": "bd04",
        "line": {
            "en": "'Umm... It's...'"
        },
        "name": "Kotori"
    },
    {
        "id": "c104",
        "line": {
            "en": "'Have you heard of gliders? Well, it's like an\\nairplane. It's used to fly through the sky.'"
        },
        "name": "Aoi"
    },
    {
        "id": "c504",
        "line": {
            "en": "'The sky...'"
        },
        "name": "Hibari"
    },
    {
        "id": "c904",
        "line": {
            "en": "'No, that's not it, Hibari! I'm not going to fly.\\nOr rather, I can't fly.'"
        },
        "name": "Kotori"
    },
    {
        "id": "cd04",
        "line": {
            "en": "'I was told just today that I couldn't do it!'"
        },
        "name": "Kotori"
    },
    {
        "id": "d104",
        "line": {
            "en": "As Kotori desperately tries to cover it up, she\\nsignals me with her glaring eyes."
        },
        "name": ""
    },
    {
        "id": "d504",
        "line": {
            "en": "'Th-That's right! We don't just fly, we build\\ngliders and stuff!'"
        },
        "name": "Aoi"
    },
    {
        "id": "d904",
        "line": {
            "en": "I don't really know why, but I follow her lead."
        },
        "name": ""
    },
    {
        "id": "dd04",
        "line": {
            "en": "'Really...?'"
        },
        "name": "Hibari"
    },
    {
        "id": "e104",
        "line": {
            "en": "'Yeah. So don't worry.'"
        },
        "name": "Kotori"
    },
    {
        "id": "e504",
        "line": {
            "en": "Hibari looked like she'd accepted it for the time\\nbeing, and didn't pursue the issue any further."
        },
        "name": ""
    },
    {
        "id": "e904",
        "line": {
            "en": "Kotori seemed relieved. It seemed like there was\\nsome reason why she shouldn't be doing club\\nactivities."
        },
        "name": ""
    },
    {
        "id": "ed04",
        "line": {
            "en": "'Anyway... sniff, sniff... Something smells\\ngood!'"
        },
        "name": "Aoi"
    },
    {
        "id": "f104",
        "line": {
            "en": "Just now, a smell that stimulated my hunger\\nstarted drifting through the air."
        },
        "name": ""
    },
    {
        "id": "f504",
        "line": {
            "en": "'I've been making paella! I was taught how while\\nI was away.'"
        },
        "name": "Hibari"
    },
    {
        "id": "f904",
        "line": {
            "en": "'There's enough for everyone, so please, enjoy.'"
        },
        "name": "Hibari"
    },
    {
        "id": "fd04",
        "line": {
            "en": "Hibari's home cooking was superb."
        },
        "name": ""
    },
    {
        "id": "0204",
        "line": {
            "en": "Paella is Spanish style cooked rice with shrimp\\nand shellfish. It was quite refined, so it went\\ndown really well with everyone in the dorm."
        },
        "name": ""
    },
    {
        "id": "0604",
        "line": {
            "en": "Also, after the main course was dessert: sweet\\nbean jelly from a famous Japanese sweets shop. It\\nwas perfect."
        },
        "name": ""
    },
    {
        "id": "0a04",
        "line": {
            "en": "Apparently, Hibari had been visiting Flying Fish\\nManor since a while back, and had been making\\nfood for Kotori and the other boarders."
        },
        "name": ""
    },
    {
        "id": "0e04",
        "line": {
            "en": "Since Kotori is disabled, Hibari had been given\\nspecial permission to come help at any time by\\nthe owner and caretaker."
        },
        "name": ""
    },
    {
        "id": "1204",
        "line": {
            "en": "Thanks to her, the level of satisfaction with\\ntonight's dinner was exceptionally high."
        },
        "name": ""
    },
    {
        "id": "1604",
        "line": {
            "en": "'Whew, I'm full!'"
        },
        "name": "Kanako"
    },
    {
        "id": "1a04",
        "line": {
            "en": "'You seem very familiar with Hibari.'"
        },
        "name": "Aoi"
    },
    {
        "id": "1e04",
        "line": {
            "en": "At the dinner table, Hibari was very open with\\nnot only her sister, but with all of the other\\nboarders."
        },
        "name": ""
    },
    {
        "id": "2204",
        "line": {
            "en": "'Hmm? Yeah, you're right.'"
        },
        "name": "Kanako"
    },
    {
        "id": "2604",
        "line": {
            "en": "'Since Kotori is like that, she takes care of her\\nas her big sister, doesn't she?'"
        },
        "name": "Kanako"
    },
    {
        "id": "2a04",
        "line": {
            "en": "I guess that when she says 'like that', she's not\\ntalking about her disability, she means her\\npersonality."
        },
        "name": ""
    },
    {
        "id": "2e04",
        "line": {
            "en": "'And she always buys souvenirs for everyone.'"
        },
        "name": "Kanako"
    },
    {
        "id": "3204",
        "line": {
            "en": "'She's got such a cute little sister, she can't\\nhelp but want to take care of her.'"
        },
        "name": "Aoi"
    },
    {
        "id": "3604",
        "line": {
            "en": "While we speak, Hibari pushes Kotori and her\\nwheelchair out of the dining hall."
        },
        "name": ""
    },
    {
        "id": "3a04",
        "line": {
            "en": "'Thank you for the meal, Hibari.'"
        },
        "name": "Aoi"
    },
    {
        "id": "3e04",
        "line": {
            "en": "'It's nothing. I'll clean everything up later, so\\nyou can just leave it there for now.'"
        },
        "name": "Hibari"
    },
    {
        "id": "4204",
        "line": {
            "en": "Even though she had just gotten back from an\\noverseas business trip, she's full of energy."
        },
        "name": ""
    },
    {
        "id": "4604",
        "line": {
            "en": "Despite her pretty and petite appearance."
        },
        "name": ""
    },
    {
        "id": "4a04",
        "line": {
            "en": "'No, I can do that.'"
        },
        "name": "Aoi"
    },
    {
        "id": "4e04",
        "line": {
            "en": "'That's right. After having such a delicious\\nmeal, you should do some work.'"
        },
        "name": "Kotori"
    },
    {
        "id": "5204",
        "line": {
            "en": "She says it like it was all her doing."
        },
        "name": ""
    },
    {
        "id": "5604",
        "line": {
            "en": "Kotori must also be proud of her sister."
        },
        "name": ""
    },
    {
        "id": "5a04",
        "line": {
            "en": "'Kotori, give me a hand later, okay?'"
        },
        "name": "Aoi"
    },
    {
        "id": "5e04",
        "line": {
            "en": "'Whaaaat...?'"
        },
        "name": "Kotori"
    },
    {
        "id": "6204",
        "line": {
            "en": "'You ate that delicious food too, didn't you?'"
        },
        "name": "Aoi"
    },
    {
        "id": "6604",
        "line": {
            "en": "'Hmph!'"
        },
        "name": "Kotori"
    },
    {
        "id": "6a04",
        "line": {
            "en": "For some reason, Kotori's reaction seems a little\\ncuter than usual. It must be her sister's\\ninfluence."
        },
        "name": ""
    },
    {
        "id": "6e04",
        "line": {
            "en": "'Okay, before that, we're going to take a bath\\ntogether.'"
        },
        "name": "Hibari"
    },
    {
        "id": "7204",
        "line": {
            "en": "'And also, we'll be sleeping together tonight!'"
        },
        "name": "Hibari"
    },
    {
        "id": "7604",
        "line": {
            "en": "'In separate beds.'"
        },
        "name": "Kotori"
    },
    {
        "id": "7a04",
        "line": {
            "en": "'Huuuuuh? Whyyyyy?'"
        },
        "name": "Hibari"
    },
    {
        "id": "7e04",
        "line": {
            "en": "'...Because it's really uncomfortable when you\\nhug me when you're half asleep.'"
        },
        "name": "Kotori"
    },
    {
        "id": "8204",
        "line": {
            "en": "'I was looking forward to that, which is why I\\ncame back in such a hurry...'"
        },
        "name": "Hibari"
    },
    {
        "id": "8604",
        "line": {
            "en": "Together with her sister, acting downhearted,\\nKotori headed to the bathroom."
        },
        "name": ""
    },
    {
        "id": "8a04",
        "line": {
            "en": "As I watch them leave like that, I remember that\\nKotori was desperately trying to cover up that\\nshe's in the Soaring Club just now."
        },
        "name": ""
    },
    {
        "id": "8e04",
        "line": {
            "en": "'(It must be because her family would worry if\\nshe were to do anything dangerous.)'"
        },
        "name": "Aoi"
    },
    {
        "id": "9204",
        "line": {
            "en": "It seemed very unnatural to me, and it preyed on\\nmy mind a little."
        },
        "name": ""
    }
]